MANIFEST.in
Makefile
README
setup.py
test/__init__.py
test/__init__.pyc
test/test_compile.py
test/test_compile.pyc
tiddlywebplugins/__init__.py
tiddlywebplugins/register.py
tiddlywebplugins.register.egg-info/PKG-INFO
tiddlywebplugins.register.egg-info/SOURCES.txt
tiddlywebplugins.register.egg-info/dependency_links.txt
tiddlywebplugins.register.egg-info/namespace_packages.txt
tiddlywebplugins.register.egg-info/not-zip-safe
tiddlywebplugins.register.egg-info/requires.txt
tiddlywebplugins.register.egg-info/top_level.txt
tiddlywebplugins/templates/register.html
tiddlywebplugins/templates/registered.html