Metadata-Version: 1.0
Name: tiddlywebplugins.register
Version: 0.3
Summary: A tiddlywebplugin for openId user registration.
Home-page: http://pypi.python.org/pypi/tiddlywebplugins.register
Author: Chris Dent
Author-email: cdent@peermore.com
License: UNKNOWN
Platform: Posix; MacOS X; Windows
